{
  "schemaVersion": 1,
  "catalogVersion": "b2f89b7eca0faeecb4531e3de26da81af6da8555dc5098e9d18001082b2ad83c",
  "products": [
    {
      "id": "sade-print-blouse",
      "sku": "HAD-CLO-001",
      "category": "Clothing",
      "name": "The Sade Print Blouse",
      "priceKobo": 4800000,
      "unit": "piece",
      "image": "/images/product-dress.jpg",
      "imageAlt": "Black woman wearing the floral Sade print blouse",
      "description": "A vivid floral blouse with an easy, polished shape for workdays, dinners and everything between.",
      "variantNote": "Sizing and availability are confirmed by your concierge before payment."
    },
    {
      "id": "abeni-sculpted-mule",
      "sku": "HAD-SHO-001",
      "category": "Shoes",
      "name": "Abeni Sculpted Mule",
      "priceKobo": 3650000,
      "unit": "pair",
      "image": "/images/product-shoes.jpg",
      "imageAlt": "Abeni sculpted mule in warm neutral leather",
      "description": "A poised slip-on mule with a sculpted heel, made to sharpen relaxed tailoring and occasion looks.",
      "variantNote": "Your preferred size and availability are confirmed before payment."
    },
    {
      "id": "ife-carryall",
      "sku": "HAD-BAG-001",
      "category": "Bags",
      "name": "The Ife Carryall",
      "priceKobo": 5200000,
      "unit": "piece",
      "image": "/images/product-bag.jpg",
      "imageAlt": "The structured Ife carryall bag in deep burgundy",
      "description": "A generous structured carryall that brings an elegant finish to office days, travel and weekends.",
      "variantNote": "Colour and availability are confirmed by your concierge before payment."
    },
    {
      "id": "ayo-serving-set",
      "sku": "HAD-KIT-001",
      "category": "Kitchen",
      "name": "Ayo Serving Set",
      "priceKobo": 2850000,
      "unit": "set",
      "image": "/images/product-kitchen.jpg",
      "imageAlt": "A coordinated serving set arranged in a bright kitchen",
      "description": "A warm considered serving set that moves comfortably from an everyday table to weekend hosting.",
      "variantNote": "Set details and availability are confirmed before payment."
    }
  ]
}
